LICENSE
README.md
econometrust-0.2.6.dist-info/METADATA
econometrust-0.2.6.dist-info/WHEEL
econometrust-0.2.6.dist-info/licenses/LICENSE
econometrust.pyi
econometrust/__init__.py
econometrust/__init__.pyi
econometrust/econometrust.cpython-312-darwin.so
econometrust/py.typed
econometrust-0.2.6.dist-info/RECORD
