Metadata-Version: 2.4
Name: econometrust
Version: 0.2.6
Classifier: Programming Language :: Python :: 3
Classifier: Programming Language :: Rust
Classifier: Operating System :: OS Independent
Classifier: License :: OSI Approved :: MIT License
Classifier: License :: OSI Approved :: Apache Software License
Classifier: Intended Audience :: Science/Research
Classifier: Topic :: Scientific/Engineering :: Mathematics
Classifier: Topic :: Scientific/Engineering :: Information Analysis
Requires-Dist: numpy>=1.21
Requires-Dist: pandas>=1.3
Requires-Dist: pytest>=8.4.1
Requires-Dist: ruff
Requires-Dist: mkdocs>=1.5.0 ; extra == 'docs'
Requires-Dist: mkdocs-material>=9.4.0 ; extra == 'docs'
Provides-Extra: docs
License-File: LICENSE
Summary: High-performance econometrics library written in Rust with Python bindings.
Keywords: econometrics,regression,ols,gls,rust,python
Author-email: Wouter de Ligt <wouterdeligt3@gmail.com>
Requires-Python: >=3.8
Project-URL: homepage, https://github.com/wdeligt/econometrust
Project-URL: repository, https://github.com/wdeligt/econometrust
Project-URL: documentation, https://wdeligt.github.io/econometrust/
